pydantic_examples/__init__.py
pydantic_examples/_version.py
pydantic_examples/py.typed
pydantic_examples/yaml.py
pydantic_examples-0.1.3.dist-info/METADATA
pydantic_examples-0.1.3.dist-info/WHEEL
pydantic_examples-0.1.3.dist-info/licenses/LICENSE
pydantic_examples-0.1.3.dist-info/RECORD
