Metadata-Version: 2.3
Name: pydantic-examples
Version: 0.1.3
Summary: Generate commented examples of serialized data from Pydantic models
Project-URL: repository, https://github.com/bneijt/pydantic-examples
Author-email: Bram Neijt <bram@neijt.nl>
License-Expression: Apache-2.0
License-File: LICENSE
Classifier: Intended Audience :: Developers
Classifier: License :: OSI Approved :: Apache Software License
Classifier: Programming Language :: Python :: 3
Classifier: Topic :: Software Development :: Documentation
Requires-Python: >=3.9
Requires-Dist: pydantic>=2.3.0
Requires-Dist: ruamel-yaml>=0.18.0
